[
    {
        "nid": "T3_Male_Archbishop_Ewan",
        "name": "Archbishop",
        "desc": "Those who's faith have been tested and achived heaven's grace. <icon>Infantry</><icon>Magic</><icon>Staff</>",
        "tier": 3,
        "movement_group": "Mages",
        "promotes_from": "Bishop_Male",
        "turns_into": [],
        "tags": [
            "Support",
            "Infantry",
            "Magic"
        ],
        "max_level": 30,
        "bases": {
            "HP": 24,
            "STR": 2,
            "MAG": 7,
            "SKL": 7,
            "SPD": 7,
            "LCK": 8,
            "DEF": 5,
            "RES": 7,
            "CON": 6,
            "MOV": 7
        },
        "growths": {
            "HP": 0,
            "STR": -14,
            "MAG": -42,
            "SKL": -42,
            "SPD": -35,
            "LCK": -53,
            "DEF": -18,
            "RES": -32,
            "CON": 0,
            "MOV": 0
        },
        "growth_bonus": {
            "HP": 90,
            "STR": 40,
            "MAG": 120,
            "SKL": 120,
            "SPD": 100,
            "LCK": 150,
            "DEF": 50,
            "RES": 90,
            "CON": 0,
            "MOV": 0
        },
        "promotion": {
            "HP": 2,
            "STR": 0,
            "MAG": 3,
            "SKL": 2,
            "SPD": 3,
            "LCK": 4,
            "DEF": 2,
            "RES": 3,
            "CON": 1,
            "MOV": -98
        },
        "max_stats": {
            "HP": 300,
            "STR": 60,
            "MAG": 74,
            "SKL": 77,
            "SPD": 78,
            "LCK": 80,
            "DEF": 69,
            "RES": 76,
            "CON": 40,
            "MOV": 15
        },
        "learned_skills": [
            [
                5,
                "Holy_Flare"
            ],
            [
                15,
                "Archbishops_Blessing"
            ],
            [
                1,
                "Cleric_Pair_Up_T3_hide"
            ],
            [
                1,
                "Crit_P20"
            ]
        ],
        "wexp_gain": {
            "Sword": [
                false,
                0,
                300
            ],
            "Lance": [
                false,
                0,
                300
            ],
            "Axe": [
                false,
                0,
                300
            ],
            "Bow": [
                false,
                0,
                300
            ],
            "Staff": [
                true,
                60,
                480
            ],
            "Light": [
                true,
                60,
                480
            ],
            "Anima": [
                true,
                60,
                480
            ],
            "Dark": [
                false,
                0,
                300
            ],
            "Default": [
                false,
                0,
                300
            ],
            "Monster": [
                false,
                0,
                null
            ]
        },
        "icon_nid": "Priest (M) Flasuban's Repal {N426, Aruka, Yggdra}",
        "icon_index": [
            0,
            0
        ],
        "map_sprite_nid": "Patriarch (M) {Unknown}-stand",
        "combat_anim_nid": "T3_Male_Archbishop",
        "fields": []
    }
]