[
    {
        "nid": "Born_Leader",
        "name": "Born Leader",
        "desc": "+10 AS and +1 bonus attack (+2 if unit doubles) to all allies within 3 spaces.",
        "icon_nid": "skill_icons",
        "icon_index": [
            3,
            52
        ],
        "components": [
            [
                "class_skill",
                null
            ],
            [
                "aura",
                "Born_Leader_Buff"
            ],
            [
                "aura_range",
                3
            ],
            [
                "aura_target",
                "ally"
            ]
        ]
    }
]