[
    {
        "nid": "Coldblooded",
        "name": "Coldblooded",
        "desc": "+35 Crit, +100 Bonus Crit damage, and half damage taken when below 75%.",
        "icon_nid": "skill_icons",
        "icon_index": [
            0,
            38
        ],
        "components": [
            [
                "class_skill",
                null
            ],
            [
                "condition",
                "unit.get_hp() <= unit.get_max_hp() // 1.3333"
            ],
            [
                "grey_if_inactive",
                null
            ],
            [
                "dynamic_crit_accuracy",
                "35"
            ],
            [
                "resist_multiplier",
                0.5
            ],
            [
                "eval_crit_additional",
                "100"
            ]
        ]
    }
]