[
    {
        "nid": "Shield_Dash_Art",
        "name": "Shield Dash",
        "desc": "<red>CA:</>Add DEF to attacks, then gain Canter (8) for 1 turn. <green>CD:2 Turns</>",
        "icon_nid": "skill_icons",
        "icon_index": [
            12,
            22
        ],
        "components": [
            [
                "class_skill",
                null
            ],
            [
                "combat_art",
                "Shield_Dash_Skill"
            ],
            [
                "Endstep_charge_increase",
                1
            ],
            [
                "build_charge",
                2
            ],
            [
                "allowed_weapons",
                "item_system.is_weapon(unit, item)"
            ]
        ]
    }
]