[
    {
        "nid": "Grab_Heart_Skill",
        "name": "Grab Heart Skill",
        "desc": "Multiplies damage dealt by 350%, If the target is alive, apply the effect of disabling enemies for two turns.",
        "icon_nid": "Skills",
        "icon_index": [
            2,
            9
        ],
        "components": [
            [
                "display_skill_icon_in_combat",
                null
            ],
            [
                "damage_multiplier",
                3.5
            ],
            [
                "give_status_after_combat_on_hit",
                "Sealed"
            ]
        ]
    }
]