[
    {
        "nid": "Anatomy",
        "name": "Anatomy",
        "desc": "",
        "icon_nid": "skill_icons",
        "icon_index": [
            14,
            14
        ],
        "components": [
            [
                "effective_damage",
                {
                    "effective_tags": [
                        "Bleeding"
                    ],
                    "effective_multiplier": 3,
                    "effective_bonus_damage": 0,
                    "show_effectiveness_flash": true,
                    "weapon_effectiveness_multiplied": true
                }
            ]
        ]
    }
]