[
    {
        "nid": "Crusaders_Blade",
        "name": "Crusader's Blade",
        "desc": "A blade used by strong crusaders.\n<green>Skills:</>Blade Sweep\n<orange>Element:</><icon>Light</>\n<red>Effective:</><icon>Frozen</><icon>Monster</><icon>Shadowblight</>\n<pink>Misc:</>Heavy, STR + LCK.",
        "icon_nid": "{LordGlenn} {ArchaneaIconProject} 2019",
        "icon_index": [
            40,
            1
        ],
        "components": [
            [
                "weapon",
                null
            ],
            [
                "target_enemy",
                null
            ],
            [
                "level_exp",
                null
            ],
            [
                "damage",
                32
            ],
            [
                "hit",
                90
            ],
            [
                "weapon_type",
                "Sword"
            ],
            [
                "weapon_rank",
                "SS"
            ],
            [
                "weight",
                27
            ],
            [
                "crit",
                10
            ],
            [
                "wexp",
                3
            ],
            [
                "min_range",
                1
            ],
            [
                "max_range",
                1
            ],
            [
                "shove",
                1
            ],
            [
                "battle_cast_anim",
                "Arrow"
            ],
            [
                "no_double",
                null
            ],
            [
                "effective_damage",
                {
                    "effective_tags": [
                        "Monster",
                        "Frozen",
                        "Shadow"
                    ],
                    "effective_multiplier": 3,
                    "effective_bonus_damage": 5,
                    "show_effectiveness_flash": true,
                    "weapon_effectiveness_multiplied": true
                }
            ],
            [
                "item_tags",
                [
                    "Blade"
                ]
            ],
            [
                "multi_status_on_equip",
                [
                    "Blade_Vantage_Effect",
                    "Blade_Sweep"
                ]
            ],
            [
                "value",
                2000
            ],
            [
                "alternate_damage_formula",
                "STR_LCK_STRONG"
            ]
        ]
    }
]