[
    {
        "nid": "Grace_Lance",
        "name": "Grace Lance",
        "desc": "An elegant lance that brings most of one's luck.\n<green>Skills:</>Goddess's Luck, Lance Guard (E)",
        "icon_nid": "{LordGlenn} {ArchaneaIconProject} 2019",
        "icon_index": [
            13,
            2
        ],
        "components": [
            [
                "weapon",
                null
            ],
            [
                "target_enemy",
                null
            ],
            [
                "min_range",
                1
            ],
            [
                "max_range",
                1
            ],
            [
                "damage",
                12
            ],
            [
                "hit",
                90
            ],
            [
                "crit",
                10
            ],
            [
                "weight",
                12
            ],
            [
                "level_exp",
                null
            ],
            [
                "weapon_type",
                "Lance"
            ],
            [
                "weapon_rank",
                "E"
            ],
            [
                "battle_cast_anim",
                "Javelin"
            ],
            [
                "prf_unit",
                [
                    "Artur"
                ]
            ],
            [
                "multi_status_on_equip",
                [
                    "Lance_Guard_E",
                    "Goddess_Luck"
                ]
            ],
            [
                "eval_available",
                "u(\"Artur\").wexp['Lance'] < 180"
            ]
        ]
    }
]