[
    {
        "nid": "Muscle_Maxxer",
        "name": "Muscle Maxxer",
        "desc": "For those who value Strength above all else.\n<blue>On Hold:</>+25% STR, but -100% MAG and -30% RES.",
        "icon_nid": "12-27-24 Accessories",
        "icon_index": [
            0,
            1
        ],
        "components": [
            [
                "multi_status_on_hold",
                [
                    "Muscle_Maxxer"
                ]
            ],
            [
                "value",
                5000
            ]
        ]
    }
]