[
    {
        "nid": "Wind_Dagger",
        "name": "Wind Dagger",
        "desc": "A knife infused with magical wind. <green>CD:2</>\n<green>Skills:</>Quick Knife<orange>Element:</><icon>Wind</><violet>Inflicts:</><icon>Bleed</>\n<red>Effective:</><icon>Flying</><icon>Seared</><pink>Misc:</>Magical, MAG + SPD/2 (<red>{e:(unit.get_stat('MAG') + (unit.get_stat('SPD')//2))}</>), +10 Crit damage,<icon>Steal</>.",
        "icon_nid": "New Generic Weapons 01-17-25",
        "icon_index": [
            3,
            0
        ],
        "components": [
            [
                "weapon",
                null
            ],
            [
                "value",
                500
            ],
            [
                "target_enemy",
                null
            ],
            [
                "min_range",
                1
            ],
            [
                "max_range",
                3
            ],
            [
                "damage",
                3
            ],
            [
                "hit",
                75
            ],
            [
                "crit",
                7
            ],
            [
                "weight",
                5
            ],
            [
                "level_exp",
                null
            ],
            [
                "weapon_type",
                "Sword"
            ],
            [
                "weapon_rank",
                "D"
            ],
            [
                "cooldown",
                2
            ],
            [
                "status_on_equip",
                "Quick_Knife"
            ],
            [
                "battle_cast_anim",
                "Wind"
            ],
            [
                "statuses_on_hit",
                [
                    "Bleeding",
                    "Bleeding_Boss"
                ]
            ],
            [
                "ignore_line_of_sight",
                null
            ],
            [
                "magic",
                null
            ],
            [
                "alternate_damage_formula",
                "MAG_SPD_MID"
            ],
            [
                "prf_tags",
                [
                    "Thief"
                ]
            ],
            [
                "effective_damage",
                {
                    "effective_tags": [
                        "Flying",
                        "Seared"
                    ],
                    "effective_multiplier": 3,
                    "effective_bonus_damage": 0,
                    "show_effectiveness_flash": true,
                    "weapon_effectiveness_multiplied": true
                }
            ],
            [
                "multi_status_on_equip",
                [
                    "Crit_Damage_Bonus_10"
                ]
            ]
        ]
    }
]