[
    {
        "nid": "Nyx_Arsenal",
        "name": "Nyx Arsenal",
        "desc": "Nyx's personal arsenal, used to fight for a just cause.\n<red>Prof:</><icon>Sword</><icon>Axe</>",
        "icon_nid": "Miria and Nyx weapons",
        "icon_index": [
            0,
            0
        ],
        "components": [
            [
                "multi_item",
                [
                    "Practicant_Bronze"
                ]
            ],
            [
                "unstealable",
                null
            ],
            [
                "prf_unit",
                [
                    "Nyx"
                ]
            ]
        ]
    }
]