[
    {
        "name": "Talk_Forde",
        "trigger": "on_talk",
        "level_nid": null,
        "condition": "check_pair('Eirika','Forde') or check_pair('Ephraim','Forde')",
        "commands": [],
        "only_once": false,
        "priority": 20,
        "_source": [
            "if;game.level.nid in ['2', '3', '4', '5', '6', '7']",
            "",
            "if;game.level_vars['SkipTalkForde'] != True",
            "add_portrait;Forde;Left;no_block",
            "add_portrait;Eirika;Right",
            "speak;Eirika;Test",
            "speak;Forde;Test",
            "multi_remove_portrait;Eirika;Forde",
            "level_var;SkipTalkForde;True",
            "else",
            "end",
            "if;game.game_vars['TrainingIndicator'] <= 3",
            "trigger_script;Global Training",
            "else",
            "trigger_script;Global No_More_Talk",
            "end",
            "if;game.game_vars['TrainingIndicator'] == 4",
            "remove_talk;Eirika;Forde",
            "remove_talk;Ephraim;Forde",
            "else",
            "end",
            "",
            "",
            "elif;game.level.nid == '5x'",
            "",
            "if;game.level_vars['SkipTalkForde'] != True",
            "add_portrait;Forde;Left;no_block",
            "add_portrait;Ephraim;Right",
            "speak;Ephraim;Any stragglers?",
            "speak;Forde;Doesn't look like it.|I don't see anyone so far.",
            "speak;Ephraim;Ok, good.|Keep your eye out for any reinforcements.",
            "speak;Forde;Sure can do boss.|Leave it to me!",
            "multi_remove_portrait;Ephraim;Forde",
            "level_var;SkipTalkForde;True",
            "else",
            "end",
            "if;game.game_vars['TrainingIndicator'] <= 3",
            "trigger_script;Global Training",
            "else",
            "trigger_script;Global No_More_Talk",
            "end",
            "if;game.game_vars['TrainingIndicator'] == 4",
            "remove_talk;Eirika;Forde",
            "remove_talk;Ephraim;Forde",
            "else",
            "end",
            "",
            "",
            "elif;game.level.nid == '8'",
            "",
            "if;game.level_vars['SkipTalkForde'] != True",
            "add_portrait;Forde;Left;no_block",
            "add_portrait;Eirika;Right",
            "if;game.check_alive(\"Franz\") or game.current_mode.permadeath != True",
            "speak;Eirika;You must be Franz's brother, right?",
            "speak;Forde;Yes!|Princess Eirika!|It's a pleasure to see you alive!",
            "speak;Eirika;He he!|Thank you!|I hope my brother hasn't pushed you too hard!",
            "speak;Forde;Nothing we can't handle!|We are knights of Renais after all!",
            "speak;Eirika;He he he!|Indeed, the finest knights I've seen!",
            "else",
            "expression;Forde;CloseEyes",
            "expression;Eirika;HalfCloseEyes",
            "speak;Eirika;...You must be Forde, right?",
            "speak;Forde;...Yes...|I'm Forde...|Franz's brother...",
            "speak;Eirika;I'm so sorry...|He was a brave soldier...",
            "speak;Forde;I know...|I bet he was...|If you excuse me, I need a moment...",
            "expression;Eirika;CloseEyes",
            "speak;Eirika;Of course...",
            "remove_portrait;Eirika",
            "speak;Forde;First Dad, then Mom...|Now Franz...|I'm all alone...",
            "end",
            "multi_remove_portrait;Eirika;Forde",
            "level_var;SkipTalkForde;True",
            "else",
            "end",
            "if;game.game_vars['TrainingIndicator'] <= 3",
            "trigger_script;Global Training",
            "else",
            "trigger_script;Global No_More_Talk",
            "end",
            "if;game.game_vars['TrainingIndicator'] == 4",
            "remove_talk;Eirika;Forde",
            "remove_talk;Ephraim;Forde",
            "else",
            "end",
            "",
            "elif;game.level.nid == '9A'",
            "",
            "if;game.level_vars['SkipTalkForde'] != True",
            "add_portrait;Forde;Left;no_block",
            "add_portrait;Eirika;Right",
            "speak;Eirika;This is our real battle together Forde.",
            "speak;Forde;Yeah, you fight completely different than Ephraim.|It was kind of refreshing actually!",
            "speak;Eirika;Oh really?",
            "speak;Forde;Yeah!|You're a lot prettier than Ephraim!|I would rather look at you than Ephraim!|Ha ha!",
            "speak;Eirika;Oh Forde!|You're teasing me!",
            "multi_remove_portrait;Eirika;Forde",
            "level_var;SkipTalkForde;True",
            "else",
            "end",
            "if;game.game_vars['TrainingIndicator'] <= 3",
            "trigger_script;Global Training",
            "else",
            "trigger_script;Global No_More_Talk",
            "end",
            "if;game.game_vars['TrainingIndicator'] == 4",
            "remove_talk;Eirika;Forde",
            "remove_talk;Ephraim;Forde",
            "else",
            "end",
            "",
            "elif;game.level.nid == '10A'",
            "",
            "if;game.level_vars['SkipTalkForde'] != True",
            "add_portrait;Forde;Left;;CloseEyes;no_block",
            "add_portrait;Eirika;Right",
            "speak;Eirika;Forde, are you taking a nap?",
            "speak;Forde;.....;no_talk",
            "speak;Eirika;Forde?",
            "speak;Forde;.....;no_talk",
            "speak;Eirika;He's in a deep slumber...",
            "multi_remove_portrait;Eirika;Forde",
            "level_var;SkipTalkForde;True",
            "else",
            "end",
            "if;game.game_vars['TrainingIndicator'] <= 3",
            "trigger_script;Global Training",
            "else",
            "trigger_script;Global No_More_Talk",
            "end",
            "if;game.game_vars['TrainingIndicator'] == 4",
            "remove_talk;Eirika;Forde",
            "remove_talk;Ephraim;Forde",
            "else",
            "end",
            "",
            "elif;game.level.nid == '11A'",
            "",
            "if;game.level_vars['SkipTalkForde'] != True",
            "add_portrait;Forde;Left;;CloseEyes;no_block",
            "add_portrait;Eirika;Right",
            "speak;Eirika;.....;no_talk",
            "speak;Forde;......;no_talk",
            "speak;Eirika;I'm not even going to try to wake him up...",
            "multi_remove_portrait;Eirika;Forde",
            "level_var;SkipTalkForde;True",
            "else",
            "end",
            "if;game.game_vars['TrainingIndicator'] <= 3",
            "trigger_script;Global Training",
            "else",
            "trigger_script;Global No_More_Talk",
            "end",
            "if;game.game_vars['TrainingIndicator'] == 4",
            "remove_talk;Eirika;Forde",
            "remove_talk;Ephraim;Forde",
            "else",
            "end",
            "",
            "elif;game.level.nid == '12A'",
            "",
            "if;game.level_vars['SkipTalkForde'] != True",
            "add_portrait;Forde;Left;;CloseEyes;no_block",
            "add_portrait;Eirika;Right",
            "speak;Eirika;How can Forde sleep by a fire like this?",
            "speak;Forde;.....;no_talk",
            "speak;Forde;...So hot...",
            "speak;Eirika;Maybe I should splash some water on him?",
            "multi_remove_portrait;Eirika;Forde",
            "level_var;SkipTalkForde;True",
            "else",
            "end",
            "if;game.game_vars['TrainingIndicator'] <= 3",
            "trigger_script;Global Training",
            "else",
            "trigger_script;Global No_More_Talk",
            "end",
            "if;game.game_vars['TrainingIndicator'] == 4",
            "remove_talk;Eirika;Forde",
            "remove_talk;Ephraim;Forde",
            "else",
            "end",
            "",
            "elif;game.level.nid == '13A'",
            "",
            "if;game.level_vars['SkipTalkForde'] != True",
            "add_portrait;Forde;Left;no_block",
            "add_portrait;Eirika;Right",
            "speak;Eirika;It's surprising to see you awake Forde.",
            "speak;Forde;Yeah...|That was a tough battle.|Couldn't afford to close my eyes for a moment.",
            "speak;Eirika;Well, thank you for helping.|We need as much man power as we can get.|Even you Forde.",
            "bop_portrait;Forde",
            "speak;Forde;Hey!|What's that's supposed to mean?!",
            "multi_remove_portrait;Eirika;Forde",
            "level_var;SkipTalkForde;True",
            "else",
            "end",
            "if;game.game_vars['TrainingIndicator'] <= 3",
            "trigger_script;Global Training",
            "else",
            "trigger_script;Global No_More_Talk",
            "end",
            "if;game.game_vars['TrainingIndicator'] == 4",
            "remove_talk;Eirika;Forde",
            "remove_talk;Ephraim;Forde",
            "else",
            "end",
            "",
            "elif;game.level.nid == '14A'",
            "",
            "if;game.level_vars['SkipTalkForde'] != True",
            "add_portrait;Forde;Left;no_block",
            "add_portrait;Eirika;Right",
            "speak;Eirika;Thank you for searching and not taking a nap, Forde.",
            "speak;Forde;This is serious business.|I'm doing what I can to help find the Queen.",
            "speak;Eirika;Thank you Forde...|Let me know if you find anything.",
            "speak;Forde;Can do, Princess.",
            "multi_remove_portrait;Eirika;Forde",
            "level_var;SkipTalkForde;True",
            "else",
            "end",
            "if;game.game_vars['TrainingIndicator'] <= 3",
            "trigger_script;Global Training",
            "else",
            "trigger_script;Global No_More_Talk",
            "end",
            "if;game.game_vars['TrainingIndicator'] == 4",
            "remove_talk;Eirika;Forde",
            "remove_talk;Ephraim;Forde",
            "else",
            "end",
            "",
            "elif;game.level.nid == '15A'",
            "",
            "if;game.level_vars['SkipTalkForde'] != True",
            "add_portrait;Forde;Left;;CloseEyes;no_block",
            "add_portrait;Eirika;Right",
            "speak;Eirika;I guess the heat got to him...|Well, at least he's sleeping in the shade...",
            "speak;Forde;.....;no_talk",
            "speak;Forde;Finally...A...Good...Nap...|Zzzzz.....",
            "multi_remove_portrait;Eirika;Forde",
            "level_var;SkipTalkForde;True",
            "else",
            "end",
            "if;game.game_vars['TrainingIndicator'] <= 3",
            "trigger_script;Global Training",
            "else",
            "trigger_script;Global No_More_Talk",
            "end",
            "if;game.game_vars['TrainingIndicator'] == 4",
            "remove_talk;Eirika;Forde",
            "remove_talk;Ephraim;Forde",
            "else",
            "end",
            "",
            "elif;game.level.nid == '16A'",
            "",
            "if;game.level_vars['SkipTalkForde'] != True",
            "add_portrait;Forde;Left;no_block",
            "add_portrait;Eirika;Right",
            "speak;Eirika;I'm surprised you're not asleep Forde, now that we are back home.",
            "speak;Forde;Oh, trust me Princess.|I would if I could, but there is too much to do for me to nap!",
            "speak;Eirika;Huh, that's pretty knightly of you.",
            "bop_portrait;Forde",
            "speak;Forde;Hey!|I didn't become a knight of Renais by doing nothing, you know!",
            "speak;Eirika;He he!|If you did, I would have been worried about our troops long ago!",
            "multi_remove_portrait;Eirika;Forde",
            "level_var;SkipTalkForde;True",
            "else",
            "end",
            "if;game.game_vars['TrainingIndicator'] <= 3",
            "trigger_script;Global Training",
            "else",
            "trigger_script;Global No_More_Talk",
            "end",
            "if;game.game_vars['TrainingIndicator'] == 4",
            "remove_talk;Eirika;Forde",
            "remove_talk;Ephraim;Forde",
            "else",
            "end",
            "",
            "elif;game.level.nid == '17A'",
            "",
            "if;game.level_vars['SkipTalkForde'] != True",
            "add_portrait;Forde;Left;;CloseEyes;no_block",
            "add_portrait;Eirika;Right",
            "expression;Eirika;HalfCloseEyes",
            "speak;Eirika;Forde!|Wake up!",
            "expression;Forde;NormalBlink",
            "bop_portrait;Forde",
            "speak;Forde;Oh!|Sorry Princess!|This just seemed like a great place to take a nap!",
            "speak;Eirika;Forde!|How can you sleep right now!|We need to find Lyon!",
            "speak;Forde;Oh...|Sorry, about that, Princess...",
            "speak;Eirika;Let me know if you find anything!",
            "expression;Forde;HalfCloseEyes",
            "speak;Forde;Ok...|Looks like that was a bad time to nap...",
            "multi_remove_portrait;Eirika;Forde",
            "level_var;SkipTalkForde;True",
            "else",
            "end",
            "if;game.game_vars['TrainingIndicator'] <= 3",
            "trigger_script;Global Training",
            "else",
            "trigger_script;Global No_More_Talk",
            "end",
            "if;game.game_vars['TrainingIndicator'] == 4",
            "remove_talk;Eirika;Forde",
            "remove_talk;Ephraim;Forde",
            "else",
            "end",
            "",
            "elif;game.level.nid == '18A'",
            "",
            "if;game.level_vars['SkipTalkForde'] != True",
            "add_portrait;Forde;Left;no_block",
            "add_portrait;Eirika;Right",
            "speak;Eirika;Forde, it's too hot here.|You better not take a nap, or you could die!",
            "speak;Forde;You're right, Princess...|As much as I'd hate to admit it.|I might not wake up if I nap here.",
            "speak;Eirika;Excatly.|Let me know if you need any water, we might be here for a while longer.",
            "speak;Forde;Thanks!|That would hit the spot actually!",
            "speak;Eirika;He he!|Coming right up then!|You know, you might be useful in enviroments like this!",
            "bop_portrait;Forde",
            "speak;Forde;Hey!|I'm always useful!",
            "speak;Forde;.....;no_talk",
            "speak;Forde;Ok, I'm mostly always useful!",
            "multi_remove_portrait;Eirika;Forde",
            "level_var;SkipTalkForde;True",
            "else",
            "end",
            "if;game.game_vars['TrainingIndicator'] <= 3",
            "trigger_script;Global Training",
            "else",
            "trigger_script;Global No_More_Talk",
            "end",
            "if;game.game_vars['TrainingIndicator'] == 4",
            "remove_talk;Eirika;Forde",
            "remove_talk;Ephraim;Forde",
            "else",
            "end",
            "",
            "elif;game.level.nid == '19A'",
            "",
            "if;game.level_vars['SkipTalkForde'] != True",
            "add_portrait;Forde;Left;;CloseEyes;no_block",
            "add_portrait;Eirika;Right",
            "speak;Eirika;I knew you would be asleep, Forde.|I brought you a blanket.",
            "speak;Forde;.....;no_talk",
            "speak;Eirika;Thank you for your help this battle, Forde.|You deserve this rest.",
            "speak;Forde;.....;no_talk",
            "speak;Eirika;Sleep well...",
            "multi_remove_portrait;Eirika;Forde",
            "level_var;SkipTalkForde;True",
            "else",
            "end",
            "if;game.game_vars['TrainingIndicator'] <= 3",
            "trigger_script;Global Training",
            "else",
            "trigger_script;Global No_More_Talk",
            "end",
            "if;game.game_vars['TrainingIndicator'] == 4",
            "remove_talk;Eirika;Forde",
            "remove_talk;Ephraim;Forde",
            "else",
            "end",
            "",
            "elif;game.level.nid == '20A'",
            "",
            "if;game.level_vars['SkipTalkForde'] != True",
            "add_portrait;Forde;Left;no_block",
            "add_portrait;Eirika;Right",
            "speak;Eirika;Forde, this could be our final battle.|Can I ask that you don't fall asleep for this next battle?|I need all the strength we can get for us to win.",
            "speak;Forde;Of course, Princess!|I can't sleep in a time like this!",
            "speak;Forde;.....;no_talk",
            "speak;Forde;Well, I probably could if I tried, but I won't sleep!|My sword is yours, Princess!",
            "speak;Eirika;Good.|I know we can win with you by my side.",
            "multi_remove_portrait;Eirika;Forde",
            "level_var;SkipTalkForde;True",
            "else",
            "end",
            "if;game.game_vars['TrainingIndicator'] <= 3",
            "trigger_script;Global Training",
            "else",
            "trigger_script;Global No_More_Talk",
            "end",
            "if;game.game_vars['TrainingIndicator'] == 4",
            "remove_talk;Eirika;Forde",
            "remove_talk;Ephraim;Forde",
            "else",
            "end",
            "",
            "elif;game.level.nid == '9B'",
            "",
            "if;game.level_vars['SkipTalkForde'] != True",
            "add_portrait;Forde;Left;no_block",
            "add_portrait;Ephraim;Right",
            "speak;Ephraim;Forde, don't tell me you're thinking of napping?",
            "speak;Forde;Oh, come on, your Highness!|We've got all of these hands to help now!|I can shut my eyes for a little bit, can't I?",
            "speak;Ephraim;We may have more troops, but there is still plenty of work to be done.|I can give you an assignment if you don't have one.",
            "speak;Forde;Alright, alright.|I've got some supplies I can deliver.|Just leave it to me.",
            "speak;Ephraim;Ok, good.|Now I better not catching you doozing off at a later time.",
            "speak;Forde;Drat...",
            "multi_remove_portrait;Ephraim;Forde",
            "level_var;SkipTalkForde;True",
            "else",
            "end",
            "if;game.game_vars['TrainingIndicator'] <= 3",
            "trigger_script;Global Training",
            "else",
            "trigger_script;Global No_More_Talk",
            "end",
            "if;game.game_vars['TrainingIndicator'] == 4",
            "remove_talk;Eirika;Forde",
            "remove_talk;Ephraim;Forde",
            "else",
            "end",
            "",
            "elif;game.level.nid == '10B'",
            "",
            "if;game.level_vars['SkipTalkForde'] != True",
            "add_portrait;Forde;Left;;CloseEyes;no_block",
            "add_portrait;Ephraim;Right",
            "speak;Ephraim;Forde.",
            "speak;Forde;.....;no_talk",
            "speak;Ephraim;.....;no_talk",
            "speak;Ephraim;Forde!",
            "speak;Forde;.....;no_talk",
            "speak;Ephraim;.....;no_talk",
            "speak;Ephraim;FORDE!",
            "expression;Forde;HalfCloseEyes",
            "bop_portrait;Forde",
            "speak;Forde;Wha-?!|Y-Yes, sir?",
            "expression;Forde;NormalBlink",
            "speak;Ephraim;Forde...|Seriously?",
            "speak;Forde;Sorry, I couldn't hear you over the sound of the waves.",
            "speak;Ephraim;I doubt that's the case.",
            "multi_remove_portrait;Ephraim;Forde",
            "level_var;SkipTalkForde;True",
            "else",
            "end",
            "if;game.game_vars['TrainingIndicator'] <= 3",
            "trigger_script;Global Training",
            "else",
            "trigger_script;Global No_More_Talk",
            "end",
            "if;game.game_vars['TrainingIndicator'] == 4",
            "remove_talk;Eirika;Forde",
            "remove_talk;Ephraim;Forde",
            "else",
            "end",
            "",
            "elif;game.level.nid == '11B'",
            "",
            "if;game.level_vars['SkipTalkForde'] != True",
            "add_portrait;Forde;Left;no_block",
            "add_portrait;Ephraim;Right",
            "speak;Ephraim;Forde, your guard shift is over.|You can go rest now.",
            "speak;Forde;Finally!|I felt like I was gonna pass out anytime now!",
            "speak;Ephraim;I'm suprised you didn't earlier.",
            "speak;Forde;Yeah...|It took...",
            "expression;Forde;HalfCloseEyes",
            "speak;Forde;A lot of willpower...|To stay...",
            "expression;Forde;CloseEyes",
            "speak;Forde;Awake...",
            "speak;Ephraim;.....;no_talk",
            "speak;Ephraim;Forde?",
            "speak;Forde;.....;no_talk",
            "speak;Ephraim;Did he just...fall asleep standing?...",
            "multi_remove_portrait;Ephraim;Forde",
            "level_var;SkipTalkForde;True",
            "else",
            "end",
            "if;game.game_vars['TrainingIndicator'] <= 3",
            "trigger_script;Global Training",
            "else",
            "trigger_script;Global No_More_Talk",
            "end",
            "if;game.game_vars['TrainingIndicator'] == 4",
            "remove_talk;Eirika;Forde",
            "remove_talk;Ephraim;Forde",
            "else",
            "end",
            "",
            "elif;game.level.nid == '12B'",
            "",
            "if;game.level_vars['SkipTalkForde'] != True",
            "add_portrait;Forde;Left;no_block",
            "add_portrait;Ephraim;Right",
            "speak;Ephraim;I have a task for you, Forde.",
            "speak;Forde;Oh yeah?|What is it, your Highness?",
            "speak;Ephraim;Some of the villagers are worried about any more monsters coming to attack.|Can I have you do a sweep around the forests?|Make sure there are no monsters that survived.",
            "speak;Forde;Leave it to me, your Highness.|I'll make sure the perimeter is safe!",
            "speak;Ephraim;Good.|I'm reminded how good of a knight you are when you're not asleep.",
            "bop_portrait;Forde",
            "speak;Forde;Hey!|I'm always a great knight!",
            "multi_remove_portrait;Ephraim;Forde",
            "level_var;SkipTalkForde;True",
            "else",
            "end",
            "if;game.game_vars['TrainingIndicator'] <= 3",
            "trigger_script;Global Training",
            "else",
            "trigger_script;Global No_More_Talk",
            "end",
            "if;game.game_vars['TrainingIndicator'] == 4",
            "remove_talk;Eirika;Forde",
            "remove_talk;Ephraim;Forde",
            "else",
            "end",
            "",
            "elif;game.level.nid == '13B'",
            "",
            "if;game.level_vars['SkipTalkForde'] != True",
            "add_portrait;Forde;Left;no_block",
            "add_portrait;Ephraim;Right",
            "speak;Ephraim;Forde.|Do you think I could've done more?|What was I lacking?",
            "speak;Forde;Prince...|You're overthinking this.|She made her choice.|A choice that neither her or you can take back anymore.|If it makes you feel better, tomorrow this will all be in the past.",
            "speak;Ephraim;I guess...",
            "speak;Forde;...Did that make you feel a little bit better?",
            "speak;Ephraim;Probably don't push it, Forde...",
            "speak;Forde;Drat...",
            "multi_remove_portrait;Ephraim;Forde",
            "level_var;SkipTalkForde;True",
            "else",
            "end",
            "if;game.game_vars['TrainingIndicator'] <= 3",
            "trigger_script;Global Training",
            "else",
            "trigger_script;Global No_More_Talk",
            "end",
            "if;game.game_vars['TrainingIndicator'] == 4",
            "remove_talk;Eirika;Forde",
            "remove_talk;Ephraim;Forde",
            "else",
            "end",
            "",
            "elif;game.level.nid == '14B'",
            "",
            "if;game.level_vars['SkipTalkForde'] != True",
            "add_portrait;Forde;Left;no_block",
            "add_portrait;Ephraim;Right",
            "speak;Forde;Did you see that?|The king just...disappeared?|Where in the world did he go?",
            "speak;Ephraim;I...don't know...|Was it an illusion?|This doesn't make any sense...",
            "speak;Forde;This could be a trap, your Highness.|We need to stay on our gaurd.",
            "speak;Ephraim;You're right.|We better keep our arms ready.|At least until we know we are clear.",
            "speak;Forde;Understood.|I'll be on standby.",
            "speak;Ephraim;Good.|Let me know if you discover anything.",
            "multi_remove_portrait;Ephraim;Forde",
            "level_var;SkipTalkForde;True",
            "else",
            "end",
            "if;game.game_vars['TrainingIndicator'] <= 3",
            "trigger_script;Global Training",
            "else",
            "trigger_script;Global No_More_Talk",
            "end",
            "if;game.game_vars['TrainingIndicator'] == 4",
            "remove_talk;Eirika;Forde",
            "remove_talk;Ephraim;Forde",
            "else",
            "end",
            "",
            "elif;game.level.nid == '15B'",
            "",
            "if;game.level_vars['SkipTalkForde'] != True",
            "add_portrait;Forde;Left;no_block",
            "add_portrait;Ephraim;Right",
            "speak;Ephraim;I guess the heat got to him.|Well, at least he's sleeping in the shade...",
            "speak;Forde;.....;no_talk",
            "speak;Forde;Finally...A...Good...Nap...|Zzzzz.....",
            "multi_remove_portrait;Ephraim;Forde",
            "level_var;SkipTalkForde;True",
            "else",
            "end",
            "if;game.game_vars['TrainingIndicator'] <= 3",
            "trigger_script;Global Training",
            "else",
            "trigger_script;Global No_More_Talk",
            "end",
            "if;game.game_vars['TrainingIndicator'] == 4",
            "remove_talk;Eirika;Forde",
            "remove_talk;Ephraim;Forde",
            "else",
            "end",
            "",
            "elif;game.level.nid == '16B'",
            "",
            "if;game.level_vars['SkipTalkForde'] != True",
            "add_portrait;Forde;Left;no_block",
            "add_portrait;Ephraim;Right",
            "speak;Ephraim;I'm suprised you're not asleep Forde, now that we are back home.",
            "speak;Forde;Oh, trust me your Highness.|I would if I could, but there is too much to do for me to nap!",
            "speak;Ephraim;Huh, that's pretty knightly of you.",
            "bop_portrait;Forde",
            "speak;Forde;Hey!|I didn't become a knight of Renais by doing nothing, you know!",
            "speak;Ephraim;If you did, I would have been worried about our troops long ago.",
            "multi_remove_portrait;Ephraim;Forde",
            "level_var;SkipTalkForde;True",
            "else",
            "end",
            "if;game.game_vars['TrainingIndicator'] <= 3",
            "trigger_script;Global Training",
            "else",
            "trigger_script;Global No_More_Talk",
            "end",
            "if;game.game_vars['TrainingIndicator'] == 4",
            "remove_talk;Eirika;Forde",
            "remove_talk;Ephraim;Forde",
            "else",
            "end",
            "",
            "elif;game.level.nid == '17B'",
            "",
            "if;game.level_vars['SkipTalkForde'] != True",
            "add_portrait;Forde;Left;no_block",
            "add_portrait;Ephraim;Right",
            "speak;Ephraim;Forde!|Wake up!",
            "expression;Forde;NormalBlink",
            "bop_portrait;Forde",
            "speak;Forde;Oh!|Sorry, your Highness!|This just seemed like a great place to take a nap!",
            "speak;Ephraim;Forde!|How can you sleep right now?!|We need to find Lyon!",
            "speak;Forde;Oh...|Sorry, about that, your High...",
            "speak;Ephraim;Let me know if you find anything!",
            "expression;Forde;HalfCloseEyes",
            "speak;Forde;Ok...|Looks like that was a bad time to nap...",
            "multi_remove_portrait;Ephraim;Forde",
            "level_var;SkipTalkForde;True",
            "else",
            "end",
            "if;game.game_vars['TrainingIndicator'] <= 3",
            "trigger_script;Global Training",
            "else",
            "trigger_script;Global No_More_Talk",
            "end",
            "if;game.game_vars['TrainingIndicator'] == 4",
            "remove_talk;Eirika;Forde",
            "remove_talk;Ephraim;Forde",
            "else",
            "end",
            "",
            "elif;game.level.nid == '18B'",
            "",
            "if;game.level_vars['SkipTalkForde'] != True",
            "add_portrait;Forde;Left;no_block",
            "add_portrait;Ephraim;Right",
            "speak;Ephraim;Forde, it's too hot here.|You better not take a nap, or you could die.",
            "speak;Forde;You're right, your Highness...|As much as I'd hate to admit it.|I might not wake up if I nap here.",
            "speak;Ephraim;Excatly.|Let me know if you need any water, we might be here for a while longer.",
            "speak;Forde;Thanks!|That would hit the spot actually!",
            "speak;Ephraim;Ok, I'll get that arranged for you then.|You know, you might be more useful in enviroments like this.",
            "bop_portrait;Forde",
            "speak;Forde;Hey!|I'm always useful!",
            "speak;Forde;.....;no_talk",
            "speak;Forde;Ok, I'm mostly always useful!",
            "multi_remove_portrait;Ephraim;Forde",
            "level_var;SkipTalkForde;True",
            "else",
            "end",
            "if;game.game_vars['TrainingIndicator'] <= 3",
            "trigger_script;Global Training",
            "else",
            "trigger_script;Global No_More_Talk",
            "end",
            "if;game.game_vars['TrainingIndicator'] == 4",
            "remove_talk;Eirika;Forde",
            "remove_talk;Ephraim;Forde",
            "else",
            "end",
            "",
            "elif;game.level.nid == '19B'",
            "",
            "if;game.level_vars['SkipTalkForde'] != True",
            "add_portrait;Forde;Left;no_block",
            "add_portrait;Ephraim;Right",
            "speak;Ephraim;I knew you would be asleep, Forde.|I arranged a blanket to be brought to you.",
            "speak;Forde;.....;no_talk",
            "speak;Ephraim;Good job on your work this battle.|You deserve this rest.",
            "speak;Forde;.....;no_talk",
            "speak;Ephraim;Don't sleep for too long, though.",
            "multi_remove_portrait;Ephraim;Forde",
            "level_var;SkipTalkForde;True",
            "else",
            "end",
            "if;game.game_vars['TrainingIndicator'] <= 3",
            "trigger_script;Global Training",
            "else",
            "trigger_script;Global No_More_Talk",
            "end",
            "if;game.game_vars['TrainingIndicator'] == 4",
            "remove_talk;Eirika;Forde",
            "remove_talk;Ephraim;Forde",
            "else",
            "end",
            "",
            "elif;game.level.nid == '20B'",
            "",
            "if;game.level_vars['SkipTalkForde'] != True",
            "add_portrait;Forde;Left;no_block",
            "add_portrait;Ephraim;Right",
            "speak;Ephraim;Forde, this could be our final battle.|Can I ask that you don't fall asleep for this next battle?|I need all the strength we can get for us to win.",
            "speak;Forde;Of course, your Highness!|I can't sleep in a time like this!",
            "speak;Forde;.....;no_talk",
            "speak;Forde;Well, I probably could if I tried, but I won't sleep!|My sword is yours, Princess!",
            "speak;Ephraim;Good.|May this be our greatest battle.",
            "multi_remove_portrait;Ephraim;Forde",
            "level_var;SkipTalkForde;True",
            "else",
            "end",
            "if;game.game_vars['TrainingIndicator'] <= 3",
            "trigger_script;Global Training",
            "else",
            "trigger_script;Global No_More_Talk",
            "end",
            "if;game.game_vars['TrainingIndicator'] == 4",
            "remove_talk;Eirika;Forde",
            "remove_talk;Ephraim;Forde",
            "else",
            "end",
            "",
            "else",
            "end"
        ],
        "nid": "Global Talk_Forde"
    }
]